{"count": 17391, "map": {"PRP$": 100, "VBG": 185, "VBD": 329, "``": 5, "VBN": 238, ",": 327, "''": 79, "VBP": 458, "WDT": 42, "JJ": 910, "WP": 32, "VBZ": 531, "DT": 1301, "#": 4, "RP": 76, "$": 72, "NN": 2600, "FW": 26, "POS": 20, ".": 1164, "TO": 263, "PRP": 1133, "RB": 1105, "-LRB-": 387, ":": 231, "NNS": 500, "NNP": 854, "VB": 899, "WRB": 115, "CC": 539, "LS": 10, "PDT": 16, "RBR": 31, "CD": 474, "EX": 36, "IN": 1348, "MD": 378, "NNPS": 10, "-RRB-": 392, "JJS": 13, "JJR": 91, "SYM": 24, "UH": 43}}