{"count": 48580, "map": {"PRP$": 529, "VBG": 989, "VBD": 1061, "``": 19, "VBN": 901, "POS": 88, "''": 263, "VBP": 1972, "WDT": 320, "JJ": 2978, "WP": 338, "VBZ": 1917, "DT": 3915, "RP": 183, "$": 19, "NN": 6068, "FW": 32, ",": 1078, ".": 2869, "TO": 1194, "PRP": 3530, "RB": 3249, "-LRB-": 252, ":": 152, "NNS": 2237, "NNP": 1110, "VB": 2338, "WRB": 350, "CC": 1357, "LS": 5, "PDT": 33, "RBS": 30, "RBR": 91, "CD": 562, "EX": 126, "IN": 4784, "WP$": 2, "MD": 819, "NNPS": 114, "-RRB-": 252, "JJS": 79, "JJR": 301, "SYM": 34, "UH": 40}}