{"count": 25487, "map": {"PRP$": 402, "VBG": 501, "VBD": 595, "``": 7, "VBN": 333, "POS": 29, "''": 131, "VBP": 1009, "WDT": 85, "JJ": 1340, "WP": 100, "VBZ": 817, "DT": 2007, "RP": 99, "$": 26, "NN": 3211, "FW": 8, ",": 764, ".": 1851, "TO": 516, "PRP": 2117, "RB": 1735, "-LRB-": 130, ":": 108, "NNS": 760, "NNP": 1036, "VB": 1089, "WRB": 220, "CC": 964, "LS": 8, "PDT": 9, "RBS": 2, "RBR": 50, "CD": 417, "EX": 51, "IN": 2150, "MD": 353, "NNPS": 26, "-RRB-": 127, "JJS": 61, "JJR": 125, "SYM": 63, "UH": 55}}